kd_tree/__init__.py
Katjas_kd_tree-0.0.4.dist-info/LICENSE
Katjas_kd_tree-0.0.4.dist-info/METADATA
Katjas_kd_tree-0.0.4.dist-info/WHEEL
Katjas_kd_tree-0.0.4.dist-info/top_level.txt
Katjas_kd_tree-0.0.4.dist-info/RECORD
