Metadata-Version: 2.1
Name: Katjas-kd-tree
Version: 0.0.4
Summary: An implementation of KD trees
Home-page: https://github.com/katjadellalibera/KD-tree-implementation
Author: Katja Della Libera
Author-email: katja.dellalibera@minerva.kgi.edu
License: UNKNOWN
Platform: UNKNOWN
Classifier: Programming Language :: Python :: 3
Classifier: License :: OSI Approved :: MIT License
Classifier: Operating System :: OS Independent
Requires-Dist: numpy
